Metadata-Version: 1.0
Name: kafkacli
Version: 0.0.7
Summary: Apache Kafka CLI utility tool.
Home-page: https://github.com/ryanyuan/kafkacli
Author: Ryan Yuan
Author-email: ryan.yuan@outlook.com
License: UNKNOWN
Platform: UNKNOWN
